extratools_image/__init__.py
extratools_image/py.typed
extratools_image-0.1.6.dist-info/METADATA
extratools_image-0.1.6.dist-info/WHEEL
extratools_image-0.1.6.dist-info/licenses/LICENSE
extratools_image-0.1.6.dist-info/RECORD
