Metadata-Version: 2.4
Name: extratools-image
Version: 0.1.6
Project-URL: Repository, https://github.com/chuanconggao/extratools-image
Author-email: Chuancong Gao <chuanconggao@users.noreply.github.com>
License-Expression: MIT
License-File: LICENSE
Requires-Python: >=3.11
Requires-Dist: backoff>=2.2.1
Requires-Dist: httpx>=0.28.1
Requires-Dist: pillow>=11.1.0
Requires-Dist: truststore>=0.10.1
